devaa/__init__.py
devaa/plotting.py
devaa/pycounts.py
devaa-0.1.0.dist-info/LICENSE.txt
devaa-0.1.0.dist-info/METADATA
devaa-0.1.0.dist-info/WHEEL
devaa-0.1.0.dist-info/top_level.txt
devaa-0.1.0.dist-info/RECORD
