Metadata-Version: 2.1
Name: devaa
Version: 0.1.0
Summary: Simple package counting number of words
Author: Andrea Nicoletta
Author-email: a.nicoletta996@gmail.com
Maintainer-email: Andrea Nicoletta <a.nicoletta996@gmail.com>
License: MIT License        
Project-URL: homepage, https://github.com/Anico2/devaa
Project-URL: Bug Tracker, https://github.com/Anico2/devaa/issues
Keywords: words,counter,foo,bar
Classifier: Development Status :: 5 - Production/Stable
Classifier: Programming Language :: Python
Requires-Python: >=3.8
License-File: LICENSE.txt
Requires-Dist: matplotlib (>=3.4.3)
Provides-Extra: test
Requires-Dist: pytest (<5.0.0) ; extra == 'test'
Requires-Dist: pytest-cov[all] ; extra == 'test'
